writersimple/__init__.py
writersimple-1.5.0.dist-info/METADATA
writersimple-1.5.0.dist-info/WHEEL
writersimple-1.5.0.dist-info/top_level.txt
writersimple-1.5.0.dist-info/RECORD
