Metadata-Version: 2.1
Name: writersimple
Version: 1.5.0
Summary: writer help write
Author: korbolajnennikolaj
Author-email: korbolajnennikolaj@gmail.com
Classifier: Programming Language :: Python :: 3.11
Classifier: License :: OSI Approved :: MIT License
Classifier: Operating System :: OS Independent
Requires-Python: >=3.7
Requires-Dist: requests >=2.25.1
